{
    "accrued_interest": "",
    "announcement_date": "2024-04-11",
    "auction_close_date": "",
    "auction_date": "",
    "auction_result_date": "",
    "auction_type": "",
    "awarded": "",
    "bid_to_cover_ratio": [
        "2.95"
    ],
    "currently_outstanding": 71861000000.0,
    "cusip": "912797JS7",
    "dated_date": null,
    "high_price": [
        "98.672917"
    ],
    "high_yield": [
        null
    ],
    "investment_rate": "5.395",
    "issue_date": "2024-04-18",
    "low_price": [
        null
    ],
    "low_yield": [
        null
    ],
    "mature_security_amount": 256981000000.0,
    "maturity_date": "2024-07-18",
    "median_price": [
        null
    ],
    "median_yield": [
        null
    ],
    "offering_amount": 70.0,
    "original_issue_date": "2024-01-18",
    "reopening_indicator": "Y",
    "results_pdf_name": [
        "R_20240415_1.pdf"
    ],
    "security_term_month_year": "",
    "security_term_week_year": "13-WEEK",
    "security_type": "BILL",
    "soma_accepted": [
        "4729771600"
    ],
    "spread": "",
    "tendered": "",
    "total_accepted": [
        "74731019900"
    ]
}