{
    "accrued_interest": "",
    "announcement_date": "2019-08-13",
    "auction_close_date": "",
    "auction_date": "",
    "auction_result_date": "",
    "auction_type": "",
    "awarded": "",
    "bid_to_cover_ratio": [
        "2.47"
    ],
    "currently_outstanding": 35001000000.0,
    "cusip": "912796VV8",
    "dated_date": null,
    "high_price": [
        "99.841333"
    ],
    "high_yield": [
        null
    ],
    "investment_rate": "2.077",
    "issue_date": "2019-08-20",
    "low_price": [
        null
    ],
    "low_yield": [
        null
    ],
    "mature_security_amount": 69995000000.0,
    "maturity_date": "2019-09-17",
    "median_price": [
        null
    ],
    "median_yield": [
        null
    ],
    "offering_amount": 55.0,
    "original_issue_date": "2019-07-23",
    "reopening_indicator": "Y",
    "results_pdf_name": [
        "R_20190815_2.pdf"
    ],
    "security_term_month_year": "",
    "security_term_week_year": "4-WEEK",
    "security_type": "BILL",
    "soma_accepted": [
        "0"
    ],
    "spread": "",
    "tendered": "",
    "total_accepted": [
        "55000219300"
    ]
}