{
    "accrued_interest": "",
    "announcement_date": "2021-01-07",
    "auction_close_date": "",
    "auction_date": "",
    "auction_result_date": "",
    "auction_type": "",
    "awarded": "",
    "bid_to_cover_ratio": [
        "3.29"
    ],
    "currently_outstanding": 38579000000.0,
    "cusip": "9127963S6",
    "dated_date": null,
    "high_price": [
        "99.954500"
    ],
    "high_yield": [
        null
    ],
    "investment_rate": "0.091",
    "issue_date": "2021-01-14",
    "low_price": [
        null
    ],
    "low_yield": [
        null
    ],
    "mature_security_amount": 165005000000.0,
    "maturity_date": "2021-07-15",
    "median_price": [
        null
    ],
    "median_yield": [
        null
    ],
    "offering_amount": 51.0,
    "original_issue_date": "2020-07-16",
    "reopening_indicator": "Y",
    "results_pdf_name": [
        "R_20210111_2.pdf"
    ],
    "security_term_month_year": "",
    "security_term_week_year": "26-WEEK",
    "security_type": "BILL",
    "soma_accepted": [
        "6208763700"
    ],
    "spread": "",
    "tendered": "",
    "total_accepted": [
        "57209487300"
    ]
}