{
    "accrued_interest": "",
    "announcement_date": "2020-06-18",
    "auction_close_date": "",
    "auction_date": "",
    "auction_result_date": "",
    "auction_type": "",
    "awarded": "",
    "bid_to_cover_ratio": [
        "3.53"
    ],
    "currently_outstanding": 27155000000.0,
    "cusip": "9127962F5",
    "dated_date": null,
    "high_price": [
        "99.863500"
    ],
    "high_yield": [
        null
    ],
    "investment_rate": "0.183",
    "issue_date": "2020-06-25",
    "low_price": [
        null
    ],
    "low_yield": [
        null
    ],
    "mature_security_amount": 144412000000.0,
    "maturity_date": "2021-03-25",
    "median_price": [
        null
    ],
    "median_yield": [
        null
    ],
    "offering_amount": 20.0,
    "original_issue_date": "2020-03-26",
    "reopening_indicator": "Y",
    "results_pdf_name": [
        "R_20200623_4.pdf"
    ],
    "security_term_month_year": "",
    "security_term_week_year": "0-WEEK",
    "security_type": "BILL",
    "soma_accepted": [
        "0"
    ],
    "spread": "",
    "tendered": "",
    "total_accepted": [
        "20000214000"
    ]
}