{
    "accrued_interest": "",
    "announcement_date": "2023-04-04",
    "auction_close_date": "",
    "auction_date": "",
    "auction_result_date": "",
    "auction_type": "",
    "awarded": "",
    "bid_to_cover_ratio": [
        "2.50"
    ],
    "currently_outstanding": 36547000000.0,
    "cusip": "912797FM4",
    "dated_date": null,
    "high_price": [
        "99.276667"
    ],
    "high_yield": [
        null
    ],
    "investment_rate": "4.762",
    "issue_date": "2023-04-11",
    "low_price": [
        null
    ],
    "low_yield": [
        null
    ],
    "mature_security_amount": 157988000000.0,
    "maturity_date": "2023-06-06",
    "median_price": [
        null
    ],
    "median_yield": [
        null
    ],
    "offering_amount": 50.0,
    "original_issue_date": "2023-02-07",
    "reopening_indicator": "Y",
    "results_pdf_name": [
        "R_20230406_2.pdf"
    ],
    "security_term_month_year": "",
    "security_term_week_year": "8-WEEK",
    "security_type": "BILL",
    "soma_accepted": [
        "1047790700"
    ],
    "spread": "",
    "tendered": "",
    "total_accepted": [
        "51047971500"
    ]
}