{
    "accrued_interest": "",
    "announcement_date": "2019-10-01",
    "auction_close_date": "",
    "auction_date": "",
    "auction_result_date": "",
    "auction_type": "",
    "awarded": "",
    "bid_to_cover_ratio": [
        "2.90"
    ],
    "currently_outstanding": 40000000000.0,
    "cusip": "912796WC9",
    "dated_date": null,
    "high_price": [
        "99.863889"
    ],
    "high_yield": [
        null
    ],
    "investment_rate": "1.782",
    "issue_date": "2019-10-08",
    "low_price": [
        null
    ],
    "low_yield": [
        null
    ],
    "mature_security_amount": 94893000000.0,
    "maturity_date": "2019-11-05",
    "median_price": [
        null
    ],
    "median_yield": [
        null
    ],
    "offering_amount": 45.0,
    "original_issue_date": "2019-09-10",
    "reopening_indicator": "Y",
    "results_pdf_name": [
        "R_20191003_2.pdf"
    ],
    "security_term_month_year": "",
    "security_term_week_year": "4-WEEK",
    "security_type": "BILL",
    "soma_accepted": [
        "52941200"
    ],
    "spread": "",
    "tendered": "",
    "total_accepted": [
        "45053148700"
    ]
}