{
    "accrued_interest": "",
    "announcement_date": "2020-06-30",
    "auction_close_date": "",
    "auction_date": "",
    "auction_result_date": "",
    "auction_type": "",
    "awarded": "",
    "bid_to_cover_ratio": [
        "3.19"
    ],
    "currently_outstanding": 103019000000.0,
    "cusip": "9127963M9",
    "dated_date": null,
    "high_price": [
        "99.991056"
    ],
    "high_yield": [
        null
    ],
    "investment_rate": "0.117",
    "issue_date": "2020-07-07",
    "low_price": [
        null
    ],
    "low_yield": [
        null
    ],
    "mature_security_amount": 149999000000.0,
    "maturity_date": "2020-08-04",
    "median_price": [
        null
    ],
    "median_yield": [
        null
    ],
    "offering_amount": 45.0,
    "original_issue_date": "2020-04-23",
    "reopening_indicator": "Y",
    "results_pdf_name": [
        "R_20200702_1.pdf"
    ],
    "security_term_month_year": "",
    "security_term_week_year": "4-WEEK",
    "security_type": "BILL",
    "soma_accepted": [
        "3218811400"
    ],
    "spread": "",
    "tendered": "",
    "total_accepted": [
        "48219281400"
    ]
}