{
    "accrued_interest": "",
    "announcement_date": "2007-01-22",
    "auction_close_date": "",
    "auction_date": "",
    "auction_result_date": "",
    "auction_type": "",
    "awarded": "",
    "bid_to_cover_ratio": [
        "2.21"
    ],
    "currently_outstanding": "",
    "cusip": "912828GF1",
    "dated_date": null,
    "high_price": [
        "99.53879"
    ],
    "high_yield": [
        "4.855"
    ],
    "investment_rate": "4.75",
    "issue_date": "2007-01-31",
    "low_price": [
        null
    ],
    "low_yield": [
        "4.796"
    ],
    "mature_security_amount": 22936.0,
    "maturity_date": "2012-01-31",
    "median_price": [
        null
    ],
    "median_yield": [
        "4.832"
    ],
    "offering_amount": 13.0,
    "original_issue_date": null,
    "reopening_indicator": "N",
    "results_pdf_name": "",
    "security_term_month_year": "",
    "security_term_week_year": "5-YEAR",
    "security_type": "NOTE",
    "soma_accepted": [
        "1931240"
    ],
    "spread": "",
    "tendered": "",
    "total_accepted": [
        "14931277"
    ]
}